[
  {
    "id": "coffee",
    "label": "Coffee",
    "icon": "☕",
    "color": "#CFB87C",
    "description": "10 core passport stops along Pearl Street and the corridor.",
    "alwaysOn": true
  },
  {
    "id": "dispensaries",
    "label": "Dispensaries",
    "icon": "🌿",
    "color": "#4A7C59",
    "description": "5 independent dispensaries — old, local, non-chain.",
    "alwaysOn": false
  },
  {
    "id": "trails",
    "label": "Trails",
    "icon": "🏔️",
    "color": "#000000",
    "description": "Boulder Creek Path and Chautauqua — hike in, walk the mall, hike out.",
    "alwaysOn": false
  },
  {
    "id": "restaurants",
    "label": "Restaurants",
    "icon": "🍽️",
    "color": "#8B3A2E",
    "description": "Food worth stopping for along and near Pearl Street.",
    "alwaysOn": false
  },
  {
    "id": "bars",
    "label": "Bars",
    "icon": "🍺",
    "color": "#5C3A1A",
    "description": "Pearl Street and Walnut Street bar corridor.",
    "alwaysOn": false
  },
  {
    "id": "music",
    "label": "Music",
    "icon": "🎸",
    "color": "#2A1A6A",
    "description": "Live music venues and the Chautauqua Auditorium concert series.",
    "alwaysOn": false
  },
  {
    "id": "shops",
    "label": "Shops",
    "icon": "🛍️",
    "color": "#4A3A2A",
    "description": "Independent boutiques and notable shops along Pearl Street.",
    "alwaysOn": false
  },
  {
    "id": "books",
    "label": "Books",
    "icon": "📚",
    "color": "#1A3A1A",
    "description": "Bookstores on and near the corridor.",
    "alwaysOn": false
  }
]
